{
  "projects": [
    {
      "name": "select arabic courses",
      "project_link": "https://abdoadel746.github.io/3in1/",
      "project_img": "../../assets/data/websites/3in1/main_page.png",
      "type": "best",
      "id": 1
    },
    {
      "name": "contact arabic courses",
      "project_link": "https://abdoadel746.github.io/3in1/",
      "project_img": "../../assets/data/websites/3in1/contact.png",
      "type": "intermediate",
      "id": 2
    },
    {
      "name": "faculty home",
      "project_link": "https://abdoadel746.github.io/course/",
      "project_img": "../../assets/data/websites/course/home.png",
      "type": "best",
      "id": 5
    },
    {
      "name": "night portfolio",
      "project_link": "https://abdoadel746.github.io/session4/",
      "project_img": "../../assets/data/websites/session4/s.png",
      "type": "best",
      "id": 6
    },
    {
      "name": "cars show",
      "project_link": "https://abdoadel746.github.io/session3/",
      "project_img": "../../assets/data/websites/session3/2.png",
      "type": "intermediate",
      "id": 7
    },
    {
      "name": "simple dashboard",
      "project_link": "https://abdoadel746.github.io/session7/",
      "project_img": "../../assets/data/websites/session 7/dashboard.png",
      "type": "beginner",
      "id": 8
    },
    {
      "name": "school landing page",
      "project_link": "https://abdoadel746.github.io/task4/",
      "project_img": "../../assets/data/websites/task4/a.png",
      "type": "intermediate",
      "id": 9
    },
    {
      "name": "login arabic courses",
      "project_link": "https://abdoadel746.github.io/3in1/",
      "project_img": "../../assets/data/websites/3in1/login.png",
      "type": "beginner",
      "id": 3
    },
    {
      "name": "arabic courses",
      "project_link": "https://abdoadel746.github.io/3in1/",
      "project_img": "../../assets/data/websites/3in1/3in1.png",
      "type": "best",
      "id": 4
    }
  ]
}
